oathldap_web/__about__.py
oathldap_web/__init__.py
oathldap_web/app.py
oathldap_web/forms.py
oathldap_web/settings.py
oathldap_web/views.py
oathldap_web/__pycache__/__about__.cpython-38.opt-1.pyc
oathldap_web/__pycache__/__init__.cpython-38.opt-1.pyc
oathldap_web/__pycache__/app.cpython-38.opt-1.pyc
oathldap_web/__pycache__/forms.cpython-38.opt-1.pyc
oathldap_web/__pycache__/settings.cpython-38.opt-1.pyc
oathldap_web/__pycache__/views.cpython-38.opt-1.pyc
oath_ldap_web-1.0.1.dist-info/LICENSE
oath_ldap_web-1.0.1.dist-info/METADATA
oath_ldap_web-1.0.1.dist-info/WHEEL
oath_ldap_web-1.0.1.dist-info/top_level.txt
oath_ldap_web-1.0.1.dist-info/RECORD
